[
  {
    "name" : "Blessed Ogbo-God Concept",
    "phone" : "080-DIGI-BAY-342",
    "image" : "1.jpg",
    "type" : "vegetables"
  },
  {
    "name" : "Resturant Collection",
    "phone" : "080-DIGI-BAY-342",
    "image" : "2.jpg",
    "type" : "meat"
  },
  {
    "name" : "Resturant",
    "phone" : "080-DIGI-BAY-342",
    "image" : "3.jpg",
    "type" : "meat"
  },
  {
    "name" : "Resturant  beans",
    "phone" : "080-DIGI-BAY-342",
    "image" : "4.jpg",
    "type" : "vegetables"
  },
  {
    "name" : "Resturant  beans",
    "phone" : "080-DIGI-BAY-342",
    "image" : "5.jpg",
    "type" : "vegetables"
  },
  {
    "name" : "Resturant  peas",
    "phone" : "080-DIGI-BAY-342",
    "image" : "6.jpg",
    "type" : "vegetables"
  },
  {
    "name" : "Resturant  peas",
    "phone" : "080-DIGI-BAY-342",
    "image" : "7.jpg",
    "type" : "vegetables"
  },
  {
    "name" : "Resturant  beef",
    "phone" : "080-DIGI-BAY-342",
    "image" : "8.jpg",
    "type" : "meat"
  },
  {
    "name" : "Resturant  soup",
    "phone" : "080-DIGI-BAY-342",
    "image" : "9.jpg",
    "type" : "soup"
  },
  {
    "name" : "Resturant tomatoes",
    "phone" : "080-DIGI-BAY-342",
    "image" : "10.jpg",
    "type" : "vegetables"
  },
  {
    "name" : "Resturant noodle soup",
    "phone" : "080-DIGI-BAY-342",
    "image" : "11.jpg",
    "type" : "soup"
  },
  {
    "name" : "Resturant and coriander soup",
    "phone" : "080-DIGI-BAY-342",
    "image" : "12.jpg",
    "type" : "soup"
  },
  {
    "name" : "Resturant tomatoes",
    "phone" : "080-DIGI-BAY-342",
    "image" : "13.jpg",
    "type" : "vegetables"
  },
  {
    "name" : "Resturant noodle soup",
    "phone" : "080-DIGI-BAY-342",
    "image" : "14.jpg",
    "type" : "soup"
  },
  {
    "name" : "Resturant and coriander soup",
    "phone" : "080-DIGI-BAY-342",
    "image" : "15.jpg",
    "type" : "soup"
  }
  
]